vstools/__init__.py
vstools/_metadata.py
vstools/py.typed
vstools/enums/__init__.py
vstools/enums/base.py
vstools/enums/color.py
vstools/enums/funcs.py
vstools/enums/generic.py
vstools/enums/other.py
vstools/enums/stubs.py
vstools/exceptions/__init__.py
vstools/exceptions/base.py
vstools/exceptions/color.py
vstools/exceptions/enum.py
vstools/exceptions/file.py
vstools/exceptions/generic.py
vstools/exceptions/module.py
vstools/functions/__init__.py
vstools/functions/check.py
vstools/functions/clip.py
vstools/functions/file.py
vstools/functions/funcs.py
vstools/functions/heuristics.py
vstools/functions/normalize.py
vstools/functions/packets.py
vstools/functions/progress.py
vstools/functions/render.py
vstools/functions/timecodes.py
vstools/functions/utils.py
vstools/types/__init__.py
vstools/types/builtins.py
vstools/types/file.py
vstools/types/funcs.py
vstools/types/generic.py
vstools/types/utils.py
vstools/utils/__file_headers.json
vstools/utils/__init__.py
vstools/utils/cache.py
vstools/utils/clips.py
vstools/utils/colors.py
vstools/utils/ffprobe.py
vstools/utils/file.py
vstools/utils/funcs.py
vstools/utils/info.py
vstools/utils/math.py
vstools/utils/mime.py
vstools/utils/mime_base.py
vstools/utils/misc.py
vstools/utils/other.py
vstools/utils/props.py
vstools/utils/ranges.py
vstools/utils/scale.py
vstools/utils/vs_enums.py
vstools/utils/vs_proxy.py
vstools-3.3.4.dist-info/LICENSE
vstools-3.3.4.dist-info/METADATA
vstools-3.3.4.dist-info/WHEEL
vstools-3.3.4.dist-info/top_level.txt
vstools-3.3.4.dist-info/RECORD
