Metadata-Version: 2.1
Name: vstools
Version: 3.3.4
Summary: Functions and utils related to VapourSynth.
Author: Setsugen no ao
Author-email: setsugen@setsugen.dev
Maintainer: Setsugen no ao
Maintainer-email: setsugen@setsugen.dev
Project-URL: Source Code, https://github.com/Jaded-Encoding-Thaumaturgy/vs-tools
Project-URL: Contact, https://discord.gg/XTpc6Fa9eB
Classifier: Programming Language :: Python :: 3
Classifier: License :: OSI Approved :: MIT License
Classifier: Operating System :: OS Independent
Requires-Python: >=3.12
License-File: LICENSE
Requires-Dist: VapourSynth>=68
Requires-Dist: stgpytools>=1.2.0
Requires-Dist: rich>=12.6.0
